fastzy-0.5.1.dist-info/METADATA
fastzy-0.5.1.dist-info/WHEEL
fastzy/__init__.py
fastzy/fastzy.pyi
fastzy/fastzy.cpython-38-darwin.so
fastzy-0.5.1.dist-info/RECORD
