Metadata-Version: 2.1
Name: fastzy
Version: 0.5.1
Summary: Python library for fast fuzzy search over a big file written in Rust
Keywords: fuzzy,levenshtein,rust
Home-Page: https://github.com/intsights/fastzy
Author: Gal Ben David <gal@intsights.com>
Author-email: Gal Ben David <gal@intsights.com>
License: MIT
Project-URL: Source Code, https://github.com/intsights/fastzy
